README.rst
pyproject.toml
setup.cfg
setup.py
markdownreveal/__init__.py
markdownreveal/commands.py
markdownreveal/config.py
markdownreveal/config.template.yaml
markdownreveal/convert.py
markdownreveal/local.py
markdownreveal/tweak.py
markdownreveal/typing.py
markdownreveal.egg-info/PKG-INFO
markdownreveal.egg-info/SOURCES.txt
markdownreveal.egg-info/dependency_links.txt
markdownreveal.egg-info/entry_points.txt
markdownreveal.egg-info/requires.txt
markdownreveal.egg-info/top_level.txt