Metadata-Version: 2.1
Name: markdownreveal
Version: 0.3.5
Summary: Create presentations with simple Markdown notation
Home-page: https://github.com/markdownreveal/markdownreveal
Author: Miguel Sánchez de León Peque
Author-email: peque@neosit.es
License: BSD License
Keywords: markdown reveal reveal.js presentation
Platform: UNKNOWN
Classifier: Development Status :: 3 - Alpha
Classifier: Topic :: Utilities
Classifier: License :: OSI Approved :: BSD License
Classifier: Programming Language :: Python :: 3
Classifier: Programming Language :: Python :: 3.5
Classifier: Programming Language :: Python :: 3.6
Classifier: Programming Language :: Python :: 3.7
Classifier: Programming Language :: Python :: Implementation :: CPython
Provides-Extra: dev
Provides-Extra: test
Provides-Extra: docs
